sloyka/.DS_Store
sloyka/__init__.py
sloyka/sample_data/gutcnina.graphml
sloyka/sample_data/sample_data.csv
sloyka/sample_data/sample_data.parquet
sloyka/sample_data/sample_data_geocoded.parquet
sloyka/sample_data/sample_data_geocoded_emotioned.parquet
sloyka/sample_data/sample_data_graph.graphml
sloyka/src/__init__.py
sloyka/src/geocoder/__init__.py
sloyka/src/geocoder/city_objects_extractor.py
sloyka/src/geocoder/geocoder.py
sloyka/src/geocoder/objects_address_extractor_by_rules.py
sloyka/src/geocoder/street_extractor.py
sloyka/src/geocoder/text_address_extractor_by_rules.py
sloyka/src/geocoder/word_form_matcher.py
sloyka/src/hyper_graph/hpgh.py
sloyka/src/risks/emotion_classifier.py
sloyka/src/risks/event_detector.py
sloyka/src/risks/regional_activity.py
sloyka/src/risks/text_classifier.py
sloyka/src/semantic_graph/__init__.py
sloyka/src/semantic_graph/g_attrs_adder.py
sloyka/src/semantic_graph/g_text_data_getter.py
sloyka/src/semantic_graph/keyword_extracter.py
sloyka/src/semantic_graph/semantic_closeness_annotator.py
sloyka/src/semantic_graph/semantic_graph_builder.py
sloyka/src/utils/constants.py
sloyka/src/utils/data_getter/__init__.py
sloyka/src/utils/data_getter/comments_reply_getter.py
sloyka/src/utils/data_getter/geo_data_getter.py
sloyka/src/utils/data_getter/historical_geo_data_getter.py
sloyka/src/utils/data_getter/location_getter.py
sloyka/src/utils/data_getter/street_getter.py
sloyka/src/utils/data_getter/vk_data_getter.py
sloyka/src/utils/data_preprocessing/__init__.py
sloyka/src/utils/data_preprocessing/preprocessor.py
sloyka/src/utils/data_processing/__init__.py
sloyka/src/utils/data_processing/area_matcher.py
sloyka/src/utils/data_processing/city_services_extract.py
sloyka/src/utils/data_processing/rule_for_natasha.py
sloyka/src/utils/exceptions/__init__.py
sloyka/src/utils/exceptions/custom_exceptions.py
sloyka/src/visual/__init__.py
sloyka/src/visual/graph_visualization.py
sloyka-0.2.5.dist-info/LICENSE.md
sloyka-0.2.5.dist-info/METADATA
sloyka-0.2.5.dist-info/WHEEL
sloyka-0.2.5.dist-info/RECORD
