Metadata-Version: 2.3
Name: sloyka
Version: 0.2.5
Summary: Library for city identity analysis from social media posts and comments
Author: sandrro, georgekontsevik
Requires-Python: >=3.10.6,<3.12
Classifier: Programming Language :: Python :: 3
Classifier: Programming Language :: Python :: 3.11
Requires-Dist: aniemore (>=1.2.3,<2.0.0)
Requires-Dist: autodocsumm (==0.2.11)
Requires-Dist: bertopic (==0.15.0)
Requires-Dist: black (==23.1.0)
Requires-Dist: flair (==0.12.2)
Requires-Dist: flake8 (==6.0.0)
Requires-Dist: folium (>=0.16.0,<0.17.0)
Requires-Dist: furo (>=2024.5.6,<2025.0.0)
Requires-Dist: fuzzywuzzy (==0.18.0)
Requires-Dist: geopandas (==0.12.2)
Requires-Dist: geopy (==2.3.0)
Requires-Dist: hypernetx (>=2.3.5,<3.0.0)
Requires-Dist: isort (==5.12.0)
Requires-Dist: jupyter (>=1.0.0,<2.0.0)
Requires-Dist: keybert (==0.8.3)
Requires-Dist: loguru (==0.7.2)
Requires-Dist: mapclassify (>=2.6.1,<3.0.0)
Requires-Dist: matplotlib (==3.7.0)
Requires-Dist: myst-parser (>=3.0.1,<4.0.0)
Requires-Dist: natasha (==1.6.0)
Requires-Dist: networkx (==3.3)
Requires-Dist: nltk (==3.8.1)
Requires-Dist: numpy (==1.25.2)
Requires-Dist: osm2geojson (==0.2.3)
Requires-Dist: osmapi (>=4.0.0,<5.0.0)
Requires-Dist: osmnx (==1.5.1)
Requires-Dist: pandarallel (==1.6.5)
Requires-Dist: pandas (==2.2.2)
Requires-Dist: pyarrow (==15.0.0)
Requires-Dist: pylint (==3.0.2)
Requires-Dist: pymorphy2 (==0.9.1)
Requires-Dist: pymorphy2-dicts-ru (==2.4.417127.4579844)
Requires-Dist: pymorphy3 (==2.0.1)
Requires-Dist: rapidfuzz (>=3.9.0,<4.0.0)
Requires-Dist: readthedocs-sphinx-search (>=0.3.2,<0.4.0)
Requires-Dist: scikit-learn (==1.4.2)
Requires-Dist: scipy (==1.12)
Requires-Dist: seaborn (==0.12.2)
Requires-Dist: shapely (==2.0.1)
Requires-Dist: spacy (==3.5.0)
Requires-Dist: sphinx (>=7.3.7,<8.0.0)
Requires-Dist: sphinx-autobuild (>=2024.4.16,<2025.0.0)
Requires-Dist: sphinx-design (>=0.6.0,<0.7.0)
Requires-Dist: sphinx-hoverxref (>=1.4.0,<2.0.0)
Requires-Dist: sphinx-inline-tabs (>=2023.4.21,<2024.0.0)
Requires-Dist: sphinx-issues (>=4.1.0,<5.0.0)
Requires-Dist: sphinx-notfound-page (>=1.0.2,<2.0.0)
Requires-Dist: sphinx-rtd-theme (>=2.0.0,<3.0.0)
Requires-Dist: testresources (>=2.0.1,<3.0.0)
Requires-Dist: torch (==2.1.1)
Requires-Dist: tqdm (==4.64.1)
Requires-Dist: transformers (==4.26.1)
Requires-Dist: vk-api (==11.9.9)
